{
  "project_info": {
    "project_number": "671539658276",
    "firebase_url": "https://smartgrains01-default-rtdb.asia-southeast1.firebasedatabase.app",
    "project_id": "smartgrains01",
    "storage_bucket": "smartgrains01.appspot.com"
  },
  "client": [
    {
      "client_info": {
        "mobilesdk_app_id": "1:671539658276:android:4d06105e845c194db2a2b1",
        "android_client_info": {
          "package_name": "com.smartgrains.krishimitra"
        }
      },
      "oauth_client": [],
      "api_key": [
        {
          "current_key": "AIzaSyBD-0qbRQ0Un4GOLFRIceqX1UNX5XYmFPc"
        }
      ],
      "services": {
        "appinvite_service": {
          "other_platform_oauth_client": []
        }
      }
    }
  ],
  "configuration_version": "1"
}